qredtea/__init__.py
qredtea/version.py
qredtea/jaxapi/__init__.py
qredtea/jaxapi/qteajaxtensor.py
qredtea/qtorchapi/__init__.py
qredtea/qtorchapi/qteaqtorchtensor.py
qredtea/symmetries/__init__.py
qredtea/symmetries/abelianlinks.py
qredtea/symmetries/abeliantensor.py
qredtea/symmetries/couplingsectors.py
qredtea/symmetries/ibarrays.py
qredtea/symmetries/irreplistings.py
qredtea/symmetries/symmetrygroups.py
qredtea/symmetries/tooling_symmetry.py
qredtea/tensorflowapi/__init__.py
qredtea/tensorflowapi/qteatftensor.py
qredtea/tooling/__init__.py
qredtea/tooling/qredteaexceptions.py
qredtea/torchapi/__init__.py
qredtea/torchapi/qteatorchtensor.py
qredtea-0.3.13.dist-info/licenses/LICENSE
qredtea-0.3.13.dist-info/METADATA
qredtea-0.3.13.dist-info/WHEEL
qredtea-0.3.13.dist-info/top_level.txt
qredtea-0.3.13.dist-info/RECORD
