Metadata-Version: 2.4
Name: qredtea
Version: 0.3.13
Summary: Quantum TEA's python tensor library beyond numpy/cupy
Home-page: https://baltig.infn.it/quantum_red_tea/py_api_quantum_red_tea.git
Author: Francesco Pio Barone, Flavio Baccari, Marco Ballarin, Alberto Coppi, Andrea De Girolamo, Daniel Jaschke, Luka Pavešić, Davide Rattacaso, Nora Reinić, Carmelo Mordini, Peter Majcen
Author-email: quantumtea@lists.infn.it
Classifier: Programming Language :: Python :: 3
Classifier: Operating System :: OS Independent
Requires-Python: >=3.11
License-File: LICENSE
Requires-Dist: numpy
Requires-Dist: scipy
Requires-Dist: matplotlib
Requires-Dist: mpmath
Requires-Dist: joblib
Requires-Dist: h5py
Requires-Dist: qtealeaves<1.8.0,>=1.7.15
Dynamic: author
Dynamic: author-email
Dynamic: classifier
Dynamic: description
Dynamic: description-content-type
Dynamic: home-page
Dynamic: license-file
Dynamic: requires-dist
Dynamic: requires-python
Dynamic: summary
